{
  "fields": [
    {
      "fieldName": "number",
      "fieldType": "String"
    }
  ],
  "relationships": [
    {
      "relationshipType": "many-to-one",
      "otherEntityName": "book",
      "relationshipName": "book",
      "otherEntityField": "title"
    },
    {
      "relationshipType": "many-to-one",
      "otherEntityName": "user",
      "relationshipName": "user",
      "otherEntityField": "login"
    }
  ],
  "entityType": "start-form",
  "processBpmnId": "OrderBookProcess",
  "domainEntityName": "Order",
  "processEntityName": "OrderBookProcess",
  "service": "serviceClass",
  "dto": "mapstruct",
  "jpaMetamodelFiltering": false,
  "readOnly": false,
  "pagination": "no",
  "name": "OrderBookProcessStartForm",
  "changelogDate": "20210401000003",
  "skipFakeData": true
}
